conjector/__init__.py
conjector/config_handler.py
conjector/entities.py
conjector/main.py
conjector/py.typed
conjector/type_converter.py
conjector-1.8.0.dist-info/LICENSE
conjector-1.8.0.dist-info/METADATA
conjector-1.8.0.dist-info/WHEEL
conjector-1.8.0.dist-info/top_level.txt
conjector-1.8.0.dist-info/RECORD
