Metadata-Version: 2.1
Name: conjector
Version: 1.8.0
Summary: Config injector for Python
Home-page: https://github.com/yar-kik/conjector
Author: Yaroslav Kikvadze
Author-email: yaroslav.kikvadze@gmail.com
License: MIT
Classifier: License :: OSI Approved :: MIT License
Classifier: Programming Language :: Python :: 3.8
Classifier: Programming Language :: Python :: 3.9
Classifier: Programming Language :: Python :: 3.10
Classifier: Programming Language :: Python :: 3.11
Requires-Python: >=3.8
License-File: LICENSE
Provides-Extra: all
Requires-Dist: PyYAML (>=6.0) ; extra == 'all'
Requires-Dist: tomli (>=1.2.0) ; extra == 'all'
Requires-Dist: ujson (>=5.0.0) ; extra == 'all'
Provides-Extra: json
Requires-Dist: ujson (>=5.0.0) ; extra == 'json'
Provides-Extra: toml
Requires-Dist: tomli (>=1.2.0) ; extra == 'toml'
Provides-Extra: yaml
Requires-Dist: PyYAML (>=6.0) ; extra == 'yaml'
